LICENSE.md
README.md
setup.py
dioptra/__init__.py
dioptra/__main__.py
dioptra/api.py
dioptra/client.py
dioptra/schemas.py
dioptra/supported_types.py
dioptra/utils.py
dioptra/inference/__init__.py
dioptra/inference/inference_runner.py
dioptra/inference/tf/__init__.py
dioptra/inference/tf/tf_runner.py
dioptra/inference/torch/__init__.py
dioptra/inference/torch/torch_runner.py
dioptra/lake/__init__.py
dioptra/lake/datasets.py
dioptra/lake/utils.py
dioptra/lake/torch/__init__.py
dioptra/lake/torch/object_store_datasets.py
dioptra/miners/__init__.py
dioptra/miners/activation_miner.py
dioptra/miners/base_miner.py
dioptra/miners/coreset_miner.py
dioptra/miners/entropy_miner.py
dioptra/miners/knn_miner.py
dioptra/miners/random_miner.py
dioptra/miners/variance_miner.py
lakeml.egg-info/PKG-INFO
lakeml.egg-info/SOURCES.txt
lakeml.egg-info/dependency_links.txt
lakeml.egg-info/requires.txt
lakeml.egg-info/top_level.txt