Metadata-Version: 2.1
Name: lakeml
Version: 1.0.5rc3
Summary: Client library to log data to Dioptra API
Home-page: https://github.com/dioptra-ai/collector-py
Author: dioptra.ai
Author-email: info@dioptra.ai
License: BSD
Project-URL: dioptra.ai, https://www.dioptra.ai
Keywords: lakeml
Platform: UNKNOWN
Classifier: Development Status :: 3 - Alpha
Classifier: Intended Audience :: Developers
Classifier: Programming Language :: Python :: 3.5
Classifier: Programming Language :: Python :: 3.6
Classifier: Programming Language :: Python :: 3.7
Classifier: Programming Language :: Python :: 3.8
Requires-Python: >=3.5.3
License-File: LICENSE.md
